<?xml version="1.0" encoding="UTF-8" standalone="yes"?>
<node artifactManager="be.nabu.eai.module.services.jdbc.JDBCServiceManager" created="2023-02-04T14:49:25.622+01:00" lastModified="2024-08-26T13:29:18.785+02:00" leaf="false" version="5">
    <environmentId>apollo</environmentId>
    <hidden>false</hidden>
    <locked>false</locked>
    <properties/>
    <references>java.lang.String</references>
    <references>java.lang.Long</references>
    <references>java.lang.Integer</references>
    <references>java.lang.Boolean</references>
    <references>be.nabu.libs.services.jdbc.AffixInput</references>
    <references>nabu.web.page.core.providers.finalizeProcess.parameters</references>
    <references>be.nabu.libs.types.api.KeyValuePair</references>
    <references>nabu.web.page.core.providers.finalizeProcess.results</references>
    <references>be.nabu.libs.services.jdbc.api.Statistic</references>
    <references>java.lang.Long</references>
    <references>java.lang.Boolean</references>
</node>
